koopmanlab/__init__.py
koopmanlab/data.py
koopmanlab/func.py
koopmanlab/model.py
koopmanlab/utils.py
koopmanlab/models/__init__.py
koopmanlab/models/kno.py
koopmanlab/models/koopmanViT.py
koopmanlab-1.0.3.dist-info/LICENSE
koopmanlab-1.0.3.dist-info/METADATA
koopmanlab-1.0.3.dist-info/WHEEL
koopmanlab-1.0.3.dist-info/top_level.txt
koopmanlab-1.0.3.dist-info/RECORD
