Metadata-Version: 2.1
Name: koopmanlab
Version: 1.0.3
Summary: A library for Koopman Neural Operator with Pytorch
Home-page: https://github.com/Koopman-Laboratory/KoopmanLab
Author: Wei Xiong, Tian Yang
Author-email: xiongw21@mails.tsinghua.edu.cn
Classifier: Programming Language :: Python :: 3
Classifier: License :: OSI Approved :: GNU General Public License v3 (GPLv3)
Classifier: Operating System :: OS Independent
Requires-Python: >=3.8.5
License-File: LICENSE
Requires-Dist: torch (>=1.10)
Requires-Dist: torchvision (>=0.13.1)
Requires-Dist: matplotlib (>=3.3.2)
Requires-Dist: numpy (>=1.14.5)
Requires-Dist: einops (==0.5.0)
Requires-Dist: timm (==0.6.11)
Requires-Dist: scipy (==1.7.3)
Requires-Dist: h5py (==3.7.0)
